globalnoc_alertmon_agent/__init__.py
globalnoc_alertmon_agent-1.0.4.dist-info/LICENSE
globalnoc_alertmon_agent-1.0.4.dist-info/METADATA
globalnoc_alertmon_agent-1.0.4.dist-info/WHEEL
globalnoc_alertmon_agent-1.0.4.dist-info/top_level.txt
globalnoc_alertmon_agent-1.0.4.dist-info/RECORD
